asciidump/__init__.py
asciidump/__main__.py
asciidump/style.css
asciidump/templates/index.html
asciidump-2022.10.1.dist-info/entry_points.txt
asciidump-2022.10.1.dist-info/WHEEL
asciidump-2022.10.1.dist-info/METADATA
asciidump-2022.10.1.dist-info/RECORD
