Metadata-Version: 2.1
Name: asciidump
Version: 2022.10.1
Summary: 
Home-page: https://github.com/honno/asciidump
License: BSD-3-Clause
Author: Matthew Barber
Author-email: quitesimplymatt@gmail.com
Requires-Python: >=3.8,<4.0
Classifier: License :: OSI Approved :: BSD License
Classifier: Programming Language :: Python :: 3
Classifier: Programming Language :: Python :: 3.10
Classifier: Programming Language :: Python :: 3.8
Classifier: Programming Language :: Python :: 3.9
Requires-Dist: Jinja2 (>=3.0.1,<4.0.0)
Requires-Dist: libsass (>=0.21.0,<0.22.0)
Requires-Dist: rich (>=10.11.0,<11.0.0)
Requires-Dist: tomli (>=2.0.0,<3.0.0)
Project-URL: Repository, https://github.com/honno/asciidump
